multi_thread_closing
