Metadata-Version: 1.1
Name: multi-thread-closing
Version: 1.0.6
Summary: this is a test package for packing python liberaries tutorial.
Home-page: https://www.github.com/ShichaoMa/MultiThreadClosing
Author: cn
Author-email: 308299269@qq.com
License: MIT
Keywords: multi thread management
Platform: UNKNOWN
Classifier: License :: OSI Approved :: MIT License
Classifier: Programming Language :: Python
Classifier: Intended Audience :: Developers
Classifier: Operating System :: OS Independent
